Metadata-Version: 2.1
Name: speedread
Version: 0.2
Summary: Speed reader in python
Home-page: https://github.com/neumann-mlucas/speedread
Author: Lucas Stefan Minuzzi Neumann
Author-email: neumannmlucas@gmail.com
License: UNKNOWN
Platform: UNKNOWN
Classifier: Programming Language :: Python :: 3
Classifier: License :: OSI Approved :: MIT License
Classifier: Operating System :: OS Independent
Requires-Python: >=3
